markdown_gds/__init__.py
markdown_gds/extension.py
markdown_gds-0.4.0.dist-info/LICENSE
markdown_gds-0.4.0.dist-info/METADATA
markdown_gds-0.4.0.dist-info/WHEEL
markdown_gds-0.4.0.dist-info/RECORD
