Metadata-Version: 2.1
Name: markdown-gds
Version: 0.4.0
Summary: A Python markdown extension for GDS
Author: Sam Dudley
Author-email: samuel.dudley@digital.trade.gov.uk
Requires-Python: >=3.10,<4.0
Classifier: Programming Language :: Python :: 3
Classifier: Programming Language :: Python :: 3.10
Classifier: Programming Language :: Python :: 3.11
Requires-Dist: Markdown (>=3.4.1,<4.0.0)
